sbmlodex/__init__.py
sbmlodex/sbmlodex.py
sbmlodex-1.0.2.dist-info/DESCRIPTION.rst
sbmlodex-1.0.2.dist-info/METADATA
sbmlodex-1.0.2.dist-info/RECORD
sbmlodex-1.0.2.dist-info/WHEEL
sbmlodex-1.0.2.dist-info/metadata.json
sbmlodex-1.0.2.dist-info/top_level.txt
