Metadata-Version: 2.0
Name: sbmlodex
Version: 1.0.2
Summary: SBML ODE extractor
Home-page: https://github.com/0u812/sbmlodex
Author: J Kyle Medley
Author-email: UNKNOWN
License: UNKNOWN
Platform: UNKNOWN
Requires-Dist: tesbml (>=5.15.0)
